adit/__init__.py
adit/__main__.py
adit/config/__init__.py
adit/config/config.py
adit/constants.py
adit/controllers/__init__.py
adit/controllers/dask_controller.py
adit/controllers/dfs_controller.py
adit/controllers/evenloop_controller.py
adit/controllers/pool_controller.py
adit/controllers/tiledb_controller.py
adit/dashboard/__init__.py
adit/dashboard/adit_webapp.py
adit/dashboard/cache/__init__.py
adit/dashboard/cache/datacache.py
adit/dashboard/cache/datahealthcache.py
adit/dashboard/cache/performancecache.py
adit/dashboard/cache/statuscache.py
adit/dashboard/models/__init__.py
adit/dashboard/models/datafeed_dashboard.py
adit/dashboard/models/datahealth_dashboard.py
adit/dashboard/models/performance_dashboard.py
adit/dashboard/models/status_dashboard.py
adit/dashboard/static/images/adit-logo.svg
adit/dashboard/static/images/aditfavicon.ico
adit/dashboard/templates/aditdata.html
adit/dashboard/templates/base.html
adit/dashboard/themes/default.yaml
adit/ingestors/__init__.py
adit/ingestors/crawlers/__init__.py
adit/ingestors/crawlers/fxcm.py
adit/ingestors/receivers/__init__.py
adit/ingestors/receivers/fxcm.py
adit/installer.py
adit/processor/__init__.py
adit/processor/metrics.py
adit/processor/models.py
adit/processor/populator.py
adit/shutdown_handler.py
adit/starter.py
adit/utils/__init__.py
adit/utils/downloaders.py
adit/utils/platform.py
adit/utils/process.py
adit/utils/proxy.py
adit-0.1.3.dist-info/WHEEL
adit-0.1.3.dist-info/METADATA
adit-0.1.3.dist-info/RECORD
